alu_sum_res_mul/fullAdder.v
module fullAdder(a,b,c,d,e);
    input a,b,c;
    output d,e;
    wire reg1,reg2,reg3;
    assign reg1=a^b;
    assign reg2=a&b;
    assign reg3=reg1&c;
    assign d=reg1^c;
    assign e=reg2|reg3;
endmodule

unidad de control/byteAdder.v
`include "fullAdder.v"
module byteAdder(A, B, c, O, o);
    input [7:0] A;
    input [7:0] B;
    input c;
    output [7:0]O;
    output o;
    wire[7:0]E;
    fullAdder U0(.a(A[0]), .b(B[0]), .c(c), .d(O[0]), .e(E[0]));
    fullAdder U1(.a(A[1]), .b(B[1]), .c(E[0]), .d(O[1]), .e(E[1]));
    fullAdder U2(.a(A[2]), .b(B[2]), .c(E[1]), .d(O[2]), .e(E[2]));
    fullAdder U3(.a(A[3]), .b(B[3]), .c(E[2]), .d(O[3]), .e(E[3]));
    fullAdder U4(.a(A[4]), .b(B[4]), .c(E[3]), .d(O[4]), .e(E[4]));
    fullAdder U5(.a(A[5]), .b(B[5]), .c(E[4]), .d(O[5]), .e(E[5]));
    fullAdder U6(.a(A[6]), .b(B[6]), .c(E[5]), .d(O[6]), .e(E[6]));
    fullAdder U7(.a(A[7]), .b(B[7]), .c(E[6]), .d(O[7]), .e(E[7]));
    assign o=E[7];
endmodule

testbenchs/basicas/byteAdder_tb.v
`timescale 1ns / 1ns 
`include "byteAdder.v"
module byteAdder_tb;
reg [7:0]A;
reg [7:0]B;
reg c;
wire [7:0]O,o;
byteAdder U0(A,B,c,O,o);
initial begin
   $dumpfile("byteAdder.vcd");   
   $dumpvars(0, byteAdder_tb);
   c=0;
   B=8'b00000001;
   A=8'b00000000; #10;
   A=8'b00000001; #10;
   A=8'b00000010; #10;
   A=8'b00000011; #10;
   A=8'b00000100; #10;
   A=8'b00000101; #10;
   A=8'b00000110; #10;
   A=8'b00000111; #10;
   A=8'b00001000; #10;
   A=8'b00001001; #10;
   A=8'b00001010; #10;
   A=8'b00001011; #10;
   A=8'b00001100; #10;
   A=8'b00001101; #10;
   A=8'b00001110; #10;
   A=8'b00001111; #10;
   A=8'b00010000; #10;
   A=8'b00010001; #10;
   A=8'b00010010; #10;
   A=8'b00010011; #10;
   A=8'b00010100; #10;
   A=8'b00010101; #10;
   A=8'b00010110; #10;
   A=8'b00010111; #10;
   A=8'b00011000; #10;
   A=8'b00011001; #10;
   A=8'b00011010; #10;
   A=8'b00011011; #10;
   A=8'b00011100; #10;
   A=8'b00011101; #10;
   A=8'b00011110; #10;
   A=8'b00011111; #10;
   A=8'b00100000; #10;
   A=8'b00100001; #10;
   A=8'b00100010; #10;
   A=8'b00100011; #10;
   A=8'b00100100; #10;
   A=8'b00100101; #10;
   A=8'b00100110; #10;
   A=8'b00100111; #10;
   A=8'b00101000; #10;
   A=8'b00101001; #10;
   A=8'b00101010; #10;
   A=8'b00101011; #10;
   A=8'b00101100; #10;
   A=8'b00101101; #10;
   A=8'b00101110; #10;
   A=8'b00101111; #10;
   A=8'b00110000; #10;
   A=8'b00110001; #10;
   A=8'b00110010; #10;
   A=8'b00110011; #10;
   A=8'b00110100; #10;
   A=8'b00110101; #10;
   A=8'b00110110; #10;
   A=8'b00110111; #10;
   A=8'b00111000; #10;
   A=8'b00111001; #10;
   A=8'b00111010; #10;
   A=8'b00111011; #10;
   A=8'b00111100; #10;
   A=8'b00111101; #10;
   A=8'b00111110; #10;
   A=8'b00111111; #10;
   A=8'b01000000; #10;
   A=8'b01000001; #10;
   A=8'b01000010; #10;
   A=8'b01000011; #10;
   A=8'b01000100; #10;
   A=8'b01000101; #10;
   A=8'b01000110; #10;
   A=8'b01000111; #10;
   A=8'b01001000; #10;
   A=8'b01001001; #10;
   A=8'b01001010; #10;
   A=8'b01001011; #10;
   A=8'b01001100; #10;
   A=8'b01001101; #10;
   A=8'b01001110; #10;
   A=8'b01001111; #10;
   A=8'b01010000; #10;
   A=8'b01010001; #10;
   A=8'b01010010; #10;
   A=8'b01010011; #10;
   A=8'b01010100; #10;
   A=8'b01010101; #10;
   A=8'b01010110; #10;
   A=8'b01010111; #10;
   A=8'b01011000; #10;
   A=8'b01011001; #10;
   A=8'b01011010; #10;
   A=8'b01011011; #10;
   A=8'b01011100; #10;
   A=8'b01011101; #10;
   A=8'b01011110; #10;
   A=8'b01011111; #10;
   A=8'b01100000; #10;
   A=8'b01100001; #10;
   A=8'b01100010; #10;
   A=8'b01100011; #10;
   A=8'b01100100; #10;
   A=8'b01100101; #10;
   A=8'b01100110; #10;
   A=8'b01100111; #10;
   A=8'b01101000; #10;
   A=8'b01101001; #10;
   A=8'b01101010; #10;
   A=8'b01101011; #10;
   A=8'b01101100; #10;
   A=8'b01101101; #10;
   A=8'b01101110; #10;
   A=8'b01101111; #10;
   A=8'b01110000; #10;
   A=8'b01110001; #10;
   A=8'b01110010; #10;
   A=8'b01110011; #10;
   A=8'b01110100; #10;
   A=8'b01110101; #10;
   A=8'b01110110; #10;
   A=8'b01110111; #10;
   A=8'b01111000; #10;
   A=8'b01111001; #10;
   A=8'b01111010; #10;
   A=8'b01111011; #10;
   A=8'b01111100; #10;
   A=8'b01111101; #10;
   A=8'b01111110; #10;
   A=8'b01111111; #10;
   A=8'b10000000; #10;
   B=8'b10000001; #10;
   B=8'b10000010; #10;
   B=8'b10000011; #10;
   B=8'b10000100; #10;
   B=8'b10000101; #10;
   B=8'b10000110; #10;
   B=8'b10000111; #10;
   B=8'b10001000; #10;
   B=8'b10001001; #10;
   B=8'b10001010; #10;
   B=8'b10001011; #10;
   B=8'b10001100; #10;
   B=8'b10001101; #10;
   B=8'b10001110; #10;
   B=8'b10001111; #10;
   B=8'b10010000; #10;
   B=8'b10010001; #10;
   B=8'b10010010; #10;
   B=8'b10010011; #10;
   B=8'b10010100; #10;
   B=8'b10010101; #10;
   B=8'b10010110; #10;
   B=8'b10010111; #10;
   B=8'b10011000; #10;
   B=8'b10011001; #10;
   B=8'b10011010; #10;
   B=8'b10011011; #10;
   B=8'b10011100; #10;
   B=8'b10011101; #10;
   B=8'b10011110; #10;
   B=8'b10011111; #10;
   B=8'b10100000; #10;
   B=8'b10100001; #10;
   B=8'b10100010; #10;
   B=8'b10100011; #10;
   B=8'b10100100; #10;
   B=8'b10100101; #10;
   B=8'b10100110; #10;
   B=8'b10100111; #10;
   B=8'b10101000; #10;
   B=8'b10101001; #10;
   B=8'b10101010; #10;
   B=8'b10101011; #10;
   B=8'b10101100; #10;
   B=8'b10101101; #10;
   B=8'b10101110; #10;
   B=8'b10101111; #10;
   B=8'b10110000; #10;
   B=8'b10110001; #10;
   B=8'b10110010; #10;
   B=8'b10110011; #10;
   B=8'b10110100; #10;
   B=8'b10110101; #10;
   B=8'b10110110; #10;
   B=8'b10110111; #10;
   B=8'b10111000; #10;
   B=8'b10111001; #10;
   B=8'b10111010; #10;
   B=8'b10111011; #10;
   B=8'b10111100; #10;
   B=8'b10111101; #10;
   B=8'b10111110; #10;
   B=8'b10111111; #10;
   B=8'b11000000; #10;
   B=8'b11000001; #10;
   B=8'b11000010; #10;
   B=8'b11000011; #10;
   B=8'b11000100; #10;
   B=8'b11000101; #10;
   B=8'b11000110; #10;
   B=8'b11000111; #10;
   B=8'b11001000; #10;
   B=8'b11001001; #10;
   B=8'b11001010; #10;
   B=8'b11001011; #10;
   B=8'b11001100; #10;
   B=8'b11001101; #10;
   B=8'b11001110; #10;
   B=8'b11001111; #10;
   B=8'b11010000; #10;
   B=8'b11010001; #10;
   B=8'b11010010; #10;
   B=8'b11010011; #10;
   B=8'b11010100; #10;
   B=8'b11010101; #10;
   B=8'b11010110; #10;
   B=8'b11010111; #10;
   B=8'b11011000; #10;
   B=8'b11011001; #10;
   B=8'b11011010; #10;
   B=8'b11011011; #10;
   B=8'b11011100; #10;
   B=8'b11011101; #10;
   B=8'b11011110; #10;
   B=8'b11011111; #10;
   B=8'b11100000; #10;
   B=8'b11100001; #10;
   B=8'b11100010; #10;
   B=8'b11100011; #10;
   B=8'b11100100; #10;
   B=8'b11100101; #10;
   B=8'b11100110; #10;
   B=8'b11100111; #10;
   B=8'b11101000; #10;
   B=8'b11101001; #10;
   B=8'b11101010; #10;
   B=8'b11101011; #10;
   B=8'b11101100; #10;
   B=8'b11101101; #10;
   B=8'b11101110; #10;
   B=8'b11101111; #10;
   B=8'b11110000; #10;
   B=8'b11110001; #10;
   B=8'b11110010; #10;
   B=8'b11110011; #10;
   B=8'b11110100; #10;
   B=8'b11110101; #10;
   B=8'b11110110; #10;
   B=8'b11110111; #10;
   B=8'b11111000; #10;
   B=8'b11111001; #10;
   B=8'b11111010; #10;
   B=8'b11111011; #10;
   B=8'b11111100; #10;
   B=8'b11111101; #10;
   B=8'b11111110; #10;
   B=8'b11111111; #10;
end
endmodule

testbenchs/basicas/byteAdder.vcd
$date
	Mon Aug 29 21:02:15 2022
$end
$version
	Icarus Verilog
$end
$timescale
	1ns
$end
$scope module byteAdder_tb $end
$var wire 8 ! o [7:0] $end
$var wire 8 " O [7:0] $end
$var reg 8 # A [7:0] $end
$var reg 8 $ B [7:0] $end
$var reg 1 % c $end
$scope module U0 $end
$var wire 8 & A [7:0] $end
$var wire 8 ' B [7:0] $end
$var wire 1 % c $end
$var wire 1 ( o $end
$var wire 8 ) O [7:0] $end
$var wire 8 * E [7:0] $end
$scope module U0 $end
$var wire 1 + a $end
$var wire 1 , b $end
$var wire 1 % c $end
$var wire 1 - d $end
$var wire 1 . e $end
$var wire 1 / reg1 $end
$var wire 1 0 reg2 $end
$var wire 1 1 reg3 $end
$upscope $end
$scope module U1 $end
$var wire 1 2 a $end
$var wire 1 3 b $end
$var wire 1 4 c $end
$var wire 1 5 d $end
$var wire 1 6 e $end
$var wire 1 7 reg1 $end
$var wire 1 8 reg2 $end
$var wire 1 9 reg3 $end
$upscope $end
$scope module U2 $end
$var wire 1 : a $end
$var wire 1 ; b $end
$var wire 1 < c $end
$var wire 1 = d $end
$var wire 1 > e $end
$var wire 1 ? reg1 $end
$var wire 1 @ reg2 $end
$var wire 1 A reg3 $end
$upscope $end
$scope module U3 $end
$var wire 1 B a $end
$var wire 1 C b $end
$var wire 1 D c $end
$var wire 1 E d $end
$var wire 1 F e $end
$var wire 1 G reg1 $end
$var wire 1 H reg2 $end
$var wire 1 I reg3 $end
$upscope $end
$scope module U4 $end
$var wire 1 J a $end
$var wire 1 K b $end
$var wire 1 L c $end
$var wire 1 M d $end
$var wire 1 N e $end
$var wire 1 O reg1 $end
$var wire 1 P reg2 $end
$var wire 1 Q reg3 $end
$upscope $end
$scope module U5 $end
$var wire 1 R a $end
$var wire 1 S b $end
$var wire 1 T c $end
$var wire 1 U d $end
$var wire 1 V e $end
$var wire 1 W reg1 $end
$var wire 1 X reg2 $end
$var wire 1 Y reg3 $end
$upscope $end
$scope module U6 $end
$var wire 1 Z a $end
$var wire 1 [ b $end
$var wire 1 \ c $end
$var wire 1 ] d $end
$var wire 1 ^ e $end
$var wire 1 _ reg1 $end
$var wire 1 ` reg2 $end
$var wire 1 a reg3 $end
$upscope $end
$scope module U7 $end
$var wire 1 b a $end
$var wire 1 c b $end
$var wire 1 d c $end
$var wire 1 e d $end
$var wire 1 f e $end
$var wire 1 g reg1 $end
$var wire 1 h reg2 $end
$var wire 1 i reg3 $end
$upscope $end
$upscope $end
$upscope $end
$enddefinitions $end
$comment Show the parameter values. $end
$dumpall
$end
#0
$dumpvars
0i
0h
0g
0f
0e
0d
0c
0b
0a
0`
0_
0^
0]
0\
0[
0Z
0Y
0X
0W
0V
0U
0T
0S
0R
0Q
0P
0O
0N
0M
0L
0K
0J
0I
0H
0G
0F
0E
0D
0C
0B
0A
0@
0?
0>
0=
0<
0;
0:
09
08
07
06
05
04
03
02
01
00
1/
0.
1-
1,
0+
b0 *
b1 )
0(
b1 '
b0 &
0%
b1 $
b0 #
b1 "
b0 !
$end
#10
15
14
b10 "
b10 )
0-
b1 *
1.
0/
10
1+
b1 #
b1 &
#20
0=
0<
04
06
1-
b0 *
0.
09
b11 "
b11 )
15
1/
00
17
0+
12
b10 #
b10 &
#30
1=
1<
16
19
05
14
b100 "
b100 )
0-
b11 *
1.
0/
10
1+
b11 #
b11 &
#40
0E
0<
0D
04
06
0>
1-
b0 *
0.
09
05
0A
b101 "
b101 )
1=
1/
00
07
1?
0+
02
1:
b100 #
b100 &
#50
15
14
b110 "
b110 )
0-
b1 *
1.
0/
10
1+
b101 #
b101 &
#60
0E
0D
0>
0A
1=
0<
04
06
1-
b0 *
0.
09
b111 "
b111 )
15
1/
00
17
0+
12
b110 #
b110 &
#70
1E
1D
1>
1A
0=
1<
16
19
05
14
b1000 "
b1000 )
0-
b111 *
1.
0/
10
1+
b111 #
b111 &
#80
0M
0<
0D
0L
04
06
0>
0F
1-
b0 *
0.
09
05
0A
0=
0I
b1001 "
b1001 )
1E
1/
00
07
0?
1G
0+
02
0:
1B
b1000 #
b1000 &
#90
15
14
b1010 "
b1010 )
0-
b1 *
1.
0/
10
1+
b1001 #
b1001 &
#100
0=
0<
04
06
1-
b0 *
0.
09
b1011 "
b1011 )
15
1/
00
17
0+
12
b1010 #
b1010 &
#110
1=
1<
16
19
05
14
b1100 "
b1100 )
0-
b11 *
1.
0/
10
1+
b1011 #
b1011 &
#120
0M
0L
0F
0I
1E
0<
0D
04
06
0>
1-
b0 *
0.
09
05
0A
b1101 "
b1101 )
1=
1/
00
07
1?
0+
02
1:
b1100 #
b1100 &
#130
15
14
b1110 "
b1110 )
0-
b1 *
1.
0/
10
1+
b1101 #
b1101 &
#140
0M
0L
0F
0I
1E
0D
0>
0A
1=
0<
04
06
1-
b0 *
0.
09
b1111 "
b1111 )
15
1/
00
17
0+
12
b1110 #
b1110 &
#150
1M
1L
1F
1I
0E
1D
1>
1A
0=
1<
16
19
05
14
b10000 "
b10000 )
0-
b1111 *
1.
0/
10
1+
b1111 #
b1111 &
#160
0U
0<
0D
0L
0T
04
06
0>
0F
0N
1-
b0 *
0.
09
05
0A
0=
0I
0E
0Q
b10001 "
b10001 )
1M
1/
00
07
0?
0G
1O
0+
02
0:
0B
1J
b10000 #
b10000 &
#170
15
14
b10010 "
b10010 )
0-
b1 *
1.
0/
10
1+
b10001 #
b10001 &
#180
0=
0<
04
06
1-
b0 *
0.
09
b10011 "
b10011 )
15
1/
00
17
0+
12
b10010 #
b10010 &
#190
1=
1<
16
19
05
14
b10100 "
b10100 )
0-
b11 *
1.
0/
10
1+
b10011 #
b10011 &
#200
0E
0<
0D
04
06
0>
1-
b0 *
0.
09
05
0A
b10101 "
b10101 )
1=
1/
00
07
1?
0+
02
1:
b10100 #
b10100 &
#210
15
14
b10110 "
b10110 )
0-
b1 *
1.
0/
10
1+
b10101 #
b10101 &
#220
0E
0D
0>
0A
1=
0<
04
06
1-
b0 *
0.
09
b10111 "
b10111 )
15
1/
00
17
0+
12
b10110 #
b10110 &
#230
1E
1D
1>
1A
0=
1<
16
19
05
14
b11000 "
b11000 )
0-
b111 *
1.
0/
10
1+
b10111 #
b10111 &
#240
0U
0T
0N
0Q
1M
0<
0D
0L
04
06
0>
0F
1-
b0 *
0.
09
05
0A
0=
0I
b11001 "
b11001 )
1E
1/
00
07
0?
1G
0+
02
0:
1B
b11000 #
b11000 &
#250
15
14
b11010 "
b11010 )
0-
b1 *
1.
0/
10
1+
b11001 #
b11001 &
#260
0=
0<
04
06
1-
b0 *
0.
09
b11011 "
b11011 )
15
1/
00
17
0+
12
b11010 #
b11010 &
#270
1=
1<
16
19
05
14
b11100 "
b11100 )
0-
b11 *
1.
0/
10
1+
b11011 #
b11011 &
#280
0U
0T
0N
0Q
1M
0L
0F
0I
1E
0<
0D
04
06
0>
1-
b0 *
0.
09
05
0A
b11101 "
b11101 )
1=
1/
00
07
1?
0+
02
1:
b11100 #
b11100 &
#290
15
14
b11110 "
b11110 )
0-
b1 *
1.
0/
10
1+
b11101 #
b11101 &
#300
0U
0T
0N
0Q
1M
0L
0F
0I
1E
0D
0>
0A
1=
0<
04
06
1-
b0 *
0.
09
b11111 "
b11111 )
15
1/
00
17
0+
12
b11110 #
b11110 &
#310
1U
1T
1N
1Q
0M
1L
1F
1I
0E
1D
1>
1A
0=
1<
16
19
05
14
b100000 "
b100000 )
0-
b11111 *
1.
0/
10
1+
b11111 #
b11111 &
#320
0]
0<
0D
0L
0T
0\
04
06
0>
0F
0N
0V
1-
b0 *
0.
09
05
0A
0=
0I
0E
0Q
0M
0Y
b100001 "
b100001 )
1U
1/
00
07
0?
0G
0O
1W
0+
02
0:
0B
0J
1R
b100000 #
b100000 &
#330
15
14
b100010 "
b100010 )
0-
b1 *
1.
0/
10
1+
b100001 #
b100001 &
#340
0=
0<
04
06
1-
b0 *
0.
09
b100011 "
b100011 )
15
1/
00
17
0+
12
b100010 #
b100010 &
#350
1=
1<
16
19
05
14
b100100 "
b100100 )
0-
b11 *
1.
0/
10
1+
b100011 #
b100011 &
#360
0E
0<
0D
04
06
0>
1-
b0 *
0.
09
05
0A
b100101 "
b100101 )
1=
1/
00
07
1?
0+
02
1:
b100100 #
b100100 &
#370
15
14
b100110 "
b100110 )
0-
b1 *
1.
0/
10
1+
b100101 #
b100101 &
#380
0E
0D
0>
0A
1=
0<
04
06
1-
b0 *
0.
09
b100111 "
b100111 )
15
1/
00
17
0+
12
b100110 #
b100110 &
#390
1E
1D
1>
1A
0=
1<
16
19
05
14
b101000 "
b101000 )
0-
b111 *
1.
0/
10
1+
b100111 #
b100111 &
#400
0M
0<
0D
0L
04
06
0>
0F
1-
b0 *
0.
09
05
0A
0=
0I
b101001 "
b101001 )
1E
1/
00
07
0?
1G
0+
02
0:
1B
b101000 #
b101000 &
#410
15
14
b101010 "
b101010 )
0-
b1 *
1.
0/
10
1+
b101001 #
b101001 &
#420
0=
0<
04
06
1-
b0 *
0.
09
b101011 "
b101011 )
15
1/
00
17
0+
12
b101010 #
b101010 &
#430
1=
1<
16
19
05
14
b101100 "
b101100 )
0-
b11 *
1.
0/
10
1+
b101011 #
b101011 &
#440
0M
0L
0F
0I
1E
0<
0D
04
06
0>
1-
b0 *
0.
09
05
0A
b101101 "
b101101 )
1=
1/
00
07
1?
0+
02
1:
b101100 #
b101100 &
#450
15
14
b101110 "
b101110 )
0-
b1 *
1.
0/
10
1+
b101101 #
b101101 &
#460
0M
0L
0F
0I
1E
0D
0>
0A
1=
0<
04
06
1-
b0 *
0.
09
b101111 "
b101111 )
15
1/
00
17
0+
12
b101110 #
b101110 &
#470
1M
1L
1F
1I
0E
1D
1>
1A
0=
1<
16
19
05
14
b110000 "
b110000 )
0-
b1111 *
1.
0/
10
1+
b101111 #
b101111 &
#480
0]
0\
0V
0Y
1U
0<
0D
0L
0T
04
06
0>
0F
0N
1-
b0 *
0.
09
05
0A
0=
0I
0E
0Q
b110001 "
b110001 )
1M
1/
00
07
0?
0G
1O
0+
02
0:
0B
1J
b110000 #
b110000 &
#490
15
14
b110010 "
b110010 )
0-
b1 *
1.
0/
10
1+
b110001 #
b110001 &
#500
0=
0<
04
06
1-
b0 *
0.
09
b110011 "
b110011 )
15
1/
00
17
0+
12
b110010 #
b110010 &
#510
1=
1<
16
19
05
14
b110100 "
b110100 )
0-
b11 *
1.
0/
10
1+
b110011 #
b110011 &
#520
0E
0<
0D
04
06
0>
1-
b0 *
0.
09
05
0A
b110101 "
b110101 )
1=
1/
00
07
1?
0+
02
1:
b110100 #
b110100 &
#530
15
14
b110110 "
b110110 )
0-
b1 *
1.
0/
10
1+
b110101 #
b110101 &
#540
0E
0D
0>
0A
1=
0<
04
06
1-
b0 *
0.
09
b110111 "
b110111 )
15
1/
00
17
0+
12
b110110 #
b110110 &
#550
1E
1D
1>
1A
0=
1<
16
19
05
14
b111000 "
b111000 )
0-
b111 *
1.
0/
10
1+
b110111 #
b110111 &
#560
0]
0\
0V
0Y
1U
0T
0N
0Q
1M
0<
0D
0L
04
06
0>
0F
1-
b0 *
0.
09
05
0A
0=
0I
b111001 "
b111001 )
1E
1/
00
07
0?
1G
0+
02
0:
1B
b111000 #
b111000 &
#570
15
14
b111010 "
b111010 )
0-
b1 *
1.
0/
10
1+
b111001 #
b111001 &
#580
0=
0<
04
06
1-
b0 *
0.
09
b111011 "
b111011 )
15
1/
00
17
0+
12
b111010 #
b111010 &
#590
1=
1<
16
19
05
14
b111100 "
b111100 )
0-
b11 *
1.
0/
10
1+
b111011 #
b111011 &
#600
0]
0\
0V
0Y
1U
0T
0N
0Q
1M
0L
0F
0I
1E
0<
0D
04
06
0>
1-
b0 *
0.
09
05
0A
b111101 "
b111101 )
1=
1/
00
07
1?
0+
02
1:
b111100 #
b111100 &
#610
15
14
b111110 "
b111110 )
0-
b1 *
1.
0/
10
1+
b111101 #
b111101 &
#620
0]
0\
0V
0Y
1U
0T
0N
0Q
1M
0L
0F
0I
1E
0D
0>
0A
1=
0<
04
06
1-
b0 *
0.
09
b111111 "
b111111 )
15
1/
00
17
0+
12
b111110 #
b111110 &
#630
1]
1\
1V
1Y
0U
1T
1N
1Q
0M
1L
1F
1I
0E
1D
1>
1A
0=
1<
16
19
05
14
b1000000 "
b1000000 )
0-
b111111 *
1.
0/
10
1+
b111111 #
b111111 &
#640
0e
0<
0D
0L
0T
0\
0d
04
06
0>
0F
0N
0V
0^
1-
b0 *
0.
09
05
0A
0=
0I
0E
0Q
0M
0Y
0U
0a
b1000001 "
b1000001 )
1]
1/
00
07
0?
0G
0O
0W
1_
0+
02
0:
0B
0J
0R
1Z
b1000000 #
b1000000 &
#650
15
14
b1000010 "
b1000010 )
0-
b1 *
1.
0/
10
1+
b1000001 #
b1000001 &
#660
0=
0<
04
06
1-
b0 *
0.
09
b1000011 "
b1000011 )
15
1/
00
17
0+
12
b1000010 #
b1000010 &
#670
1=
1<
16
19
05
14
b1000100 "
b1000100 )
0-
b11 *
1.
0/
10
1+
b1000011 #
b1000011 &
#680
0E
0<
0D
04
06
0>
1-
b0 *
0.
09
05
0A
b1000101 "
b1000101 )
1=
1/
00
07
1?
0+
02
1:
b1000100 #
b1000100 &
#690
15
14
b1000110 "
b1000110 )
0-
b1 *
1.
0/
10
1+
b1000101 #
b1000101 &
#700
0E
0D
0>
0A
1=
0<
04
06
1-
b0 *
0.
09
b1000111 "
b1000111 )
15
1/
00
17
0+
12
b1000110 #
b1000110 &
#710
1E
1D
1>
1A
0=
1<
16
19
05
14
b1001000 "
b1001000 )
0-
b111 *
1.
0/
10
1+
b1000111 #
b1000111 &
#720
0M
0<
0D
0L
04
06
0>
0F
1-
b0 *
0.
09
05
0A
0=
0I
b1001001 "
b1001001 )
1E
1/
00
07
0?
1G
0+
02
0:
1B
b1001000 #
b1001000 &
#730
15
14
b1001010 "
b1001010 )
0-
b1 *
1.
0/
10
1+
b1001001 #
b1001001 &
#740
0=
0<
04
06
1-
b0 *
0.
09
b1001011 "
b1001011 )
15
1/
00
17
0+
12
b1001010 #
b1001010 &
#750
1=
1<
16
19
05
14
b1001100 "
b1001100 )
0-
b11 *
1.
0/
10
1+
b1001011 #
b1001011 &
#760
0M
0L
0F
0I
1E
0<
0D
04
06
0>
1-
b0 *
0.
09
05
0A
b1001101 "
b1001101 )
1=
1/
00
07
1?
0+
02
1:
b1001100 #
b1001100 &
#770
15
14
b1001110 "
b1001110 )
0-
b1 *
1.
0/
10
1+
b1001101 #
b1001101 &
#780
0M
0L
0F
0I
1E
0D
0>
0A
1=
0<
04
06
1-
b0 *
0.
09
b1001111 "
b1001111 )
15
1/
00
17
0+
12
b1001110 #
b1001110 &
#790
1M
1L
1F
1I
0E
1D
1>
1A
0=
1<
16
19
05
14
b1010000 "
b1010000 )
0-
b1111 *
1.
0/
10
1+
b1001111 #
b1001111 &
#800
0U
0<
0D
0L
0T
04
06
0>
0F
0N
1-
b0 *
0.
09
05
0A
0=
0I
0E
0Q
b1010001 "
b1010001 )
1M
1/
00
07
0?
0G
1O
0+
02
0:
0B
1J
b1010000 #
b1010000 &
#810
15
14
b1010010 "
b1010010 )
0-
b1 *
1.
0/
10
1+
b1010001 #
b1010001 &
#820
0=
0<
04
06
1-
b0 *
0.
09
b1010011 "
b1010011 )
15
1/
00
17
0+
12
b1010010 #
b1010010 &
#830
1=
1<
16
19
05
14
b1010100 "
b1010100 )
0-
b11 *
1.
0/
10
1+
b1010011 #
b1010011 &
#840
0E
0<
0D
04
06
0>
1-
b0 *
0.
09
05
0A
b1010101 "
b1010101 )
1=
1/
00
07
1?
0+
02
1:
b1010100 #
b1010100 &
#850
15
14
b1010110 "
b1010110 )
0-
b1 *
1.
0/
10
1+
b1010101 #
b1010101 &
#860
0E
0D
0>
0A
1=
0<
04
06
1-
b0 *
0.
09
b1010111 "
b1010111 )
15
1/
00
17
0+
12
b1010110 #
b1010110 &
#870
1E
1D
1>
1A
0=
1<
16
19
05
14
b1011000 "
b1011000 )
0-
b111 *
1.
0/
10
1+
b1010111 #
b1010111 &
#880
0U
0T
0N
0Q
1M
0<
0D
0L
04
06
0>
0F
1-
b0 *
0.
09
05
0A
0=
0I
b1011001 "
b1011001 )
1E
1/
00
07
0?
1G
0+
02
0:
1B
b1011000 #
b1011000 &
#890
15
14
b1011010 "
b1011010 )
0-
b1 *
1.
0/
10
1+
b1011001 #
b1011001 &
#900
0=
0<
04
06
1-
b0 *
0.
09
b1011011 "
b1011011 )
15
1/
00
17
0+
12
b1011010 #
b1011010 &
#910
1=
1<
16
19
05
14
b1011100 "
b1011100 )
0-
b11 *
1.
0/
10
1+
b1011011 #
b1011011 &
#920
0U
0T
0N
0Q
1M
0L
0F
0I
1E
0<
0D
04
06
0>
1-
b0 *
0.
09
05
0A
b1011101 "
b1011101 )
1=
1/
00
07
1?
0+
02
1:
b1011100 #
b1011100 &
#930
15
14
b1011110 "
b1011110 )
0-
b1 *
1.
0/
10
1+
b1011101 #
b1011101 &
#940
0U
0T
0N
0Q
1M
0L
0F
0I
1E
0D
0>
0A
1=
0<
04
06
1-
b0 *
0.
09
b1011111 "
b1011111 )
15
1/
00
17
0+
12
b1011110 #
b1011110 &
#950
1U
1T
1N
1Q
0M
1L
1F
1I
0E
1D
1>
1A
0=
1<
16
19
05
14
b1100000 "
b1100000 )
0-
b11111 *
1.
0/
10
1+
b1011111 #
b1011111 &
#960
0e
0d
0^
0a
1]
0<
0D
0L
0T
0\
04
06
0>
0F
0N
0V
1-
b0 *
0.
09
05
0A
0=
0I
0E
0Q
0M
0Y
b1100001 "
b1100001 )
1U
1/
00
07
0?
0G
0O
1W
0+
02
0:
0B
0J
1R
b1100000 #
b1100000 &
#970
15
14
b1100010 "
b1100010 )
0-
b1 *
1.
0/
10
1+
b1100001 #
b1100001 &
#980
0=
0<
04
06
1-
b0 *
0.
09
b1100011 "
b1100011 )
15
1/
00
17
0+
12
b1100010 #
b1100010 &
#990
1=
1<
16
19
05
14
b1100100 "
b1100100 )
0-
b11 *
1.
0/
10
1+
b1100011 #
b1100011 &
#1000
0E
0<
0D
04
06
0>
1-
b0 *
0.
09
05
0A
b1100101 "
b1100101 )
1=
1/
00
07
1?
0+
02
1:
b1100100 #
b1100100 &
#1010
15
14
b1100110 "
b1100110 )
0-
b1 *
1.
0/
10
1+
b1100101 #
b1100101 &
#1020
0E
0D
0>
0A
1=
0<
04
06
1-
b0 *
0.
09
b1100111 "
b1100111 )
15
1/
00
17
0+
12
b1100110 #
b1100110 &
#1030
1E
1D
1>
1A
0=
1<
16
19
05
14
b1101000 "
b1101000 )
0-
b111 *
1.
0/
10
1+
b1100111 #
b1100111 &
#1040
0M
0<
0D
0L
04
06
0>
0F
1-
b0 *
0.
09
05
0A
0=
0I
b1101001 "
b1101001 )
1E
1/
00
07
0?
1G
0+
02
0:
1B
b1101000 #
b1101000 &
#1050
15
14
b1101010 "
b1101010 )
0-
b1 *
1.
0/
10
1+
b1101001 #
b1101001 &
#1060
0=
0<
04
06
1-
b0 *
0.
09
b1101011 "
b1101011 )
15
1/
00
17
0+
12
b1101010 #
b1101010 &
#1070
1=
1<
16
19
05
14
b1101100 "
b1101100 )
0-
b11 *
1.
0/
10
1+
b1101011 #
b1101011 &
#1080
0M
0L
0F
0I
1E
0<
0D
04
06
0>
1-
b0 *
0.
09
05
0A
b1101101 "
b1101101 )
1=
1/
00
07
1?
0+
02
1:
b1101100 #
b1101100 &
#1090
15
14
b1101110 "
b1101110 )
0-
b1 *
1.
0/
10
1+
b1101101 #
b1101101 &
#1100
0M
0L
0F
0I
1E
0D
0>
0A
1=
0<
04
06
1-
b0 *
0.
09
b1101111 "
b1101111 )
15
1/
00
17
0+
12
b1101110 #
b1101110 &
#1110
1M
1L
1F
1I
0E
1D
1>
1A
0=
1<
16
19
05
14
b1110000 "
b1110000 )
0-
b1111 *
1.
0/
10
1+
b1101111 #
b1101111 &
#1120
0e
0d
0^
0a
1]
0\
0V
0Y
1U
0<
0D
0L
0T
04
06
0>
0F
0N
1-
b0 *
0.
09
05
0A
0=
0I
0E
0Q
b1110001 "
b1110001 )
1M
1/
00
07
0?
0G
1O
0+
02
0:
0B
1J
b1110000 #
b1110000 &
#1130
15
14
b1110010 "
b1110010 )
0-
b1 *
1.
0/
10
1+
b1110001 #
b1110001 &
#1140
0=
0<
04
06
1-
b0 *
0.
09
b1110011 "
b1110011 )
15
1/
00
17
0+
12
b1110010 #
b1110010 &
#1150
1=
1<
16
19
05
14
b1110100 "
b1110100 )
0-
b11 *
1.
0/
10
1+
b1110011 #
b1110011 &
#1160
0E
0<
0D
04
06
0>
1-
b0 *
0.
09
05
0A
b1110101 "
b1110101 )
1=
1/
00
07
1?
0+
02
1:
b1110100 #
b1110100 &
#1170
15
14
b1110110 "
b1110110 )
0-
b1 *
1.
0/
10
1+
b1110101 #
b1110101 &
