programas/restadorCompleto.v
module restadorCompleto(a, b, inBorr, d, outBorr );
    input a, b, inBorr;
    output d, outBorr;
    wire wire1, wire2, wire3;
    assign reg1=a^b;
    assign reg2=~(a)&b;
    assign reg3=~(reg1)&inBorr;
    assign d=reg1^inBorr;
    assign outBorr=reg2|reg3;
endmodule

alu_sum_res_mul/ByteSub.v

module byteSub(A, B, c, O, o);
    input [7:0] A;
    input [7:0] B;
    input c;
    output [7:0]O;
    output o;
    wire[7:0]E;
    restadorCompleto U0(.a(A[0]), .b(B[0]), .inBorr(c), .d(O[0]), .outBorr(E[0]));
    restadorCompleto U1(.a(A[1]), .b(B[1]), .inBorr(E[0]), .d(O[1]), .outBorr(E[1]));
    restadorCompleto U2(.a(A[2]), .b(B[2]), .inBorr(E[1]), .d(O[2]), .outBorr(E[2]));
    restadorCompleto U3(.a(A[3]), .b(B[3]), .inBorr(E[2]), .d(O[3]), .outBorr(E[3]));
    restadorCompleto U4(.a(A[4]), .b(B[4]), .inBorr(E[3]), .d(O[4]), .outBorr(E[4]));
    restadorCompleto U5(.a(A[5]), .b(B[5]), .inBorr(E[4]), .d(O[5]), .outBorr(E[5]));
    restadorCompleto U6(.a(A[6]), .b(B[6]), .inBorr(E[5]), .d(O[6]), .outBorr(E[6]));
    restadorCompleto U7(.a(A[7]), .b(B[7]), .inBorr(E[6]), .d(O[7]), .outBorr(E[7]));
    assign o=E[7];
endmodule

testbenchs/basicas/byteSub_tb.v
`timescale 1ns / 1ns 
`include "byteSub.v"
module byteSub_tb;
reg [7:0]A;
reg [7:0]B;
reg c;
wire [7:0]O,o;
byteSub U0(A,B,c,O,o);
initial begin
   $dumpfile("byteSub.vcd");   
   $dumpvars(0, byteSub_tb);
   c=0;
   B=8'b00000001;
   A=8'b00000000; #10;
   A=8'b00000001; #10;
   A=8'b00000010; #10;
   A=8'b00000011; #10;
   A=8'b00000100; #10;
   A=8'b00000101; #10;
   A=8'b00000110; #10;
   A=8'b00000111; #10;
   A=8'b00001000; #10;
   A=8'b00001001; #10;
   A=8'b00001010; #10;
   A=8'b00001011; #10;
   A=8'b00001100; #10;
   A=8'b00001101; #10;
   A=8'b00001110; #10;
   A=8'b00001111; #10;
   A=8'b00010000; #10;
   A=8'b00010001; #10;
   A=8'b00010010; #10;
   A=8'b00010011; #10;
   A=8'b00010100; #10;
   A=8'b00010101; #10;
   A=8'b00010110; #10;
   A=8'b00010111; #10;
   A=8'b00011000; #10;
   A=8'b00011001; #10;
   A=8'b00011010; #10;
   A=8'b00011011; #10;
   A=8'b00011100; #10;
   A=8'b00011101; #10;
   A=8'b00011110; #10;
   A=8'b00011111; #10;
   A=8'b00100000; #10;
   A=8'b00100001; #10;
   A=8'b00100010; #10;
   A=8'b00100011; #10;
   A=8'b00100100; #10;
   A=8'b00100101; #10;
   A=8'b00100110; #10;
   A=8'b00100111; #10;
   A=8'b00101000; #10;
   A=8'b00101001; #10;
   A=8'b00101010; #10;
   A=8'b00101011; #10;
   A=8'b00101100; #10;
   A=8'b00101101; #10;
   A=8'b00101110; #10;
   A=8'b00101111; #10;
   A=8'b00110000; #10;
   A=8'b00110001; #10;
   A=8'b00110010; #10;
   A=8'b00110011; #10;
   A=8'b00110100; #10;
   A=8'b00110101; #10;
   A=8'b00110110; #10;
   A=8'b00110111; #10;
   A=8'b00111000; #10;
   A=8'b00111001; #10;
   A=8'b00111010; #10;
   A=8'b00111011; #10;
   A=8'b00111100; #10;
   A=8'b00111101; #10;
   A=8'b00111110; #10;
   A=8'b00111111; #10;
   A=8'b01000000; #10;
   A=8'b01000001; #10;
   A=8'b01000010; #10;
   A=8'b01000011; #10;
   A=8'b01000100; #10;
   A=8'b01000101; #10;
   A=8'b01000110; #10;
   A=8'b01000111; #10;
   A=8'b01001000; #10;
   A=8'b01001001; #10;
   A=8'b01001010; #10;
   A=8'b01001011; #10;
   A=8'b01001100; #10;
   A=8'b01001101; #10;
   A=8'b01001110; #10;
   A=8'b01001111; #10;
   A=8'b01010000; #10;
   A=8'b01010001; #10;
   A=8'b01010010; #10;
   A=8'b01010011; #10;
   A=8'b01010100; #10;
   A=8'b01010101; #10;
   A=8'b01010110; #10;
   A=8'b01010111; #10;
   A=8'b01011000; #10;
   A=8'b01011001; #10;
   A=8'b01011010; #10;
   A=8'b01011011; #10;
   A=8'b01011100; #10;
   A=8'b01011101; #10;
   A=8'b01011110; #10;
   A=8'b01011111; #10;
   A=8'b01100000; #10;
   A=8'b01100001; #10;
   A=8'b01100010; #10;
   A=8'b01100011; #10;
   A=8'b01100100; #10;
   A=8'b01100101; #10;
   A=8'b01100110; #10;
   A=8'b01100111; #10;
   A=8'b01101000; #10;
   A=8'b01101001; #10;
   A=8'b01101010; #10;
   A=8'b01101011; #10;
   A=8'b01101100; #10;
   A=8'b01101101; #10;
   A=8'b01101110; #10;
   A=8'b01101111; #10;
   A=8'b01110000; #10;
   A=8'b01110001; #10;
   A=8'b01110010; #10;
   A=8'b01110011; #10;
   A=8'b01110100; #10;
   A=8'b01110101; #10;
   A=8'b01110110; #10;
   A=8'b01110111; #10;
   A=8'b01111000; #10;
   A=8'b01111001; #10;
   A=8'b01111010; #10;
   A=8'b01111011; #10;
   A=8'b01111100; #10;
   A=8'b01111101; #10;
   A=8'b01111110; #10;
   A=8'b01111111; #10;
   A=8'b10000000; #10;
   B=8'b10000001; #10;
   B=8'b10000010; #10;
   B=8'b10000011; #10;
   B=8'b10000100; #10;
   B=8'b10000101; #10;
   B=8'b10000110; #10;
   B=8'b10000111; #10;
   B=8'b10001000; #10;
   B=8'b10001001; #10;
   B=8'b10001010; #10;
   B=8'b10001011; #10;
   B=8'b10001100; #10;
   B=8'b10001101; #10;
   B=8'b10001110; #10;
   B=8'b10001111; #10;
   B=8'b10010000; #10;
   B=8'b10010001; #10;
   B=8'b10010010; #10;
   B=8'b10010011; #10;
   B=8'b10010100; #10;
   B=8'b10010101; #10;
   B=8'b10010110; #10;
   B=8'b10010111; #10;
   B=8'b10011000; #10;
   B=8'b10011001; #10;
   B=8'b10011010; #10;
   B=8'b10011011; #10;
   B=8'b10011100; #10;
   B=8'b10011101; #10;
   B=8'b10011110; #10;
   B=8'b10011111; #10;
   B=8'b10100000; #10;
   B=8'b10100001; #10;
   B=8'b10100010; #10;
   B=8'b10100011; #10;
   B=8'b10100100; #10;
   B=8'b10100101; #10;
   B=8'b10100110; #10;
   B=8'b10100111; #10;
   B=8'b10101000; #10;
   B=8'b10101001; #10;
   B=8'b10101010; #10;
   B=8'b10101011; #10;
   B=8'b10101100; #10;
   B=8'b10101101; #10;
   B=8'b10101110; #10;
   B=8'b10101111; #10;
   B=8'b10110000; #10;
   B=8'b10110001; #10;
   B=8'b10110010; #10;
   B=8'b10110011; #10;
   B=8'b10110100; #10;
   B=8'b10110101; #10;
   B=8'b10110110; #10;
   B=8'b10110111; #10;
   B=8'b10111000; #10;
   B=8'b10111001; #10;
   B=8'b10111010; #10;
   B=8'b10111011; #10;
   B=8'b10111100; #10;
   B=8'b10111101; #10;
   B=8'b10111110; #10;
   B=8'b10111111; #10;
   B=8'b11000000; #10;
   B=8'b11000001; #10;
   B=8'b11000010; #10;
   B=8'b11000011; #10;
   B=8'b11000100; #10;
   B=8'b11000101; #10;
   B=8'b11000110; #10;
   B=8'b11000111; #10;
   B=8'b11001000; #10;
   B=8'b11001001; #10;
   B=8'b11001010; #10;
   B=8'b11001011; #10;
   B=8'b11001100; #10;
   B=8'b11001101; #10;
   B=8'b11001110; #10;
   B=8'b11001111; #10;
   B=8'b11010000; #10;
   B=8'b11010001; #10;
   B=8'b11010010; #10;
   B=8'b11010011; #10;
   B=8'b11010100; #10;
   B=8'b11010101; #10;
   B=8'b11010110; #10;
   B=8'b11010111; #10;
   B=8'b11011000; #10;
   B=8'b11011001; #10;
   B=8'b11011010; #10;
   B=8'b11011011; #10;
   B=8'b11011100; #10;
   B=8'b11011101; #10;
   B=8'b11011110; #10;
   B=8'b11011111; #10;
   B=8'b11100000; #10;
   B=8'b11100001; #10;
   B=8'b11100010; #10;
   B=8'b11100011; #10;
   B=8'b11100100; #10;
   B=8'b11100101; #10;
   B=8'b11100110; #10;
   B=8'b11100111; #10;
   B=8'b11101000; #10;
   B=8'b11101001; #10;
   B=8'b11101010; #10;
   B=8'b11101011; #10;
   B=8'b11101100; #10;
   B=8'b11101101; #10;
   B=8'b11101110; #10;
   B=8'b11101111; #10;
   B=8'b11110000; #10;
   B=8'b11110001; #10;
   B=8'b11110010; #10;
   B=8'b11110011; #10;
   B=8'b11110100; #10;
   B=8'b11110101; #10;
   B=8'b11110110; #10;
   B=8'b11110111; #10;
   B=8'b11111000; #10;
   B=8'b11111001; #10;
   B=8'b11111010; #10;
   B=8'b11111011; #10;
   B=8'b11111100; #10;
   B=8'b11111101; #10;
   B=8'b11111110; #10;
   B=8'b11111111; #10;
end
endmodule

testbenchs/basicas/byteSub.vcd
$date
	Wed Nov 09 17:01:27 2022
$end
$version
	Icarus Verilog
$end
$timescale
	1ns
$end
$scope module byteSub_tb $end
$var wire 8 ! o [7:0] $end
$var wire 8 " O [7:0] $end
$var reg 8 # A [7:0] $end
$var reg 8 $ B [7:0] $end
$var reg 1 % c $end
$scope module U0 $end
$var wire 8 & A [7:0] $end
$var wire 8 ' B [7:0] $end
$var wire 1 % c $end
$var wire 1 ( o $end
$var wire 8 ) O [7:0] $end
$var wire 8 * E [7:0] $end
$scope module U0 $end
$var wire 1 + a $end
$var wire 1 , b $end
$var wire 1 - d $end
$var wire 1 % inBorr $end
$var wire 1 . outBorr $end
$var wire 1 / reg1 $end
$var wire 1 0 reg2 $end
$var wire 1 1 reg3 $end
$upscope $end
$scope module U1 $end
$var wire 1 2 a $end
$var wire 1 3 b $end
$var wire 1 4 d $end
$var wire 1 5 inBorr $end
$var wire 1 6 outBorr $end
$var wire 1 7 reg1 $end
$var wire 1 8 reg2 $end
$var wire 1 9 reg3 $end
$upscope $end
$scope module U2 $end
$var wire 1 : a $end
$var wire 1 ; b $end
$var wire 1 < d $end
$var wire 1 = inBorr $end
$var wire 1 > outBorr $end
$var wire 1 ? reg1 $end
$var wire 1 @ reg2 $end
$var wire 1 A reg3 $end
$upscope $end
$scope module U3 $end
$var wire 1 B a $end
$var wire 1 C b $end
$var wire 1 D d $end
$var wire 1 E inBorr $end
$var wire 1 F outBorr $end
$var wire 1 G reg1 $end
$var wire 1 H reg2 $end
$var wire 1 I reg3 $end
$upscope $end
$scope module U4 $end
$var wire 1 J a $end
$var wire 1 K b $end
$var wire 1 L d $end
$var wire 1 M inBorr $end
$var wire 1 N outBorr $end
$var wire 1 O reg1 $end
$var wire 1 P reg2 $end
$var wire 1 Q reg3 $end
$upscope $end
$scope module U5 $end
$var wire 1 R a $end
$var wire 1 S b $end
$var wire 1 T d $end
$var wire 1 U inBorr $end
$var wire 1 V outBorr $end
$var wire 1 W reg1 $end
$var wire 1 X reg2 $end
$var wire 1 Y reg3 $end
$upscope $end
$scope module U6 $end
$var wire 1 Z a $end
$var wire 1 [ b $end
$var wire 1 \ d $end
$var wire 1 ] inBorr $end
$var wire 1 ^ outBorr $end
$var wire 1 _ reg1 $end
$var wire 1 ` reg2 $end
$var wire 1 a reg3 $end
$upscope $end
$scope module U7 $end
$var wire 1 b a $end
$var wire 1 c b $end
$var wire 1 d d $end
$var wire 1 e inBorr $end
$var wire 1 f outBorr $end
$var wire 1 g reg1 $end
$var wire 1 h reg2 $end
$var wire 1 i reg3 $end
$upscope $end
$upscope $end
$upscope $end
$enddefinitions $end
#0
$dumpvars
1i
0h
0g
1f
1e
1d
0c
0b
1a
0`
0_
1^
1]
1\
0[
0Z
1Y
0X
0W
1V
1U
1T
0S
0R
1Q
0P
0O
1N
1M
1L
0K
0J
1I
0H
0G
1F
1E
1D
0C
0B
1A
0@
0?
1>
1=
1<
0;
0:
19
08
07
16
15
14
03
02
01
10
1/
1.
1-
1,
0+
b11111111 *
b11111111 )
1(
b1 '
b0 &
0%
b1 $
b0 #
b11111111 "
b1 !
$end
#10
b0 !
0(
0f
0i
0d
0e
0^
0a
0\
0]
0V
0Y
0T
0U
0N
0Q
0L
0M
0F
0I
0D
0E
0>
0A
0<
0=
06
09
04
05
b0 *
0.
b0 "
b0 )
0-
00
0/
1+
b1 #
b1 &
#20
15
b1 *
1.
1-
10
b1 "
b1 )
04
1/
17
0+
12
b10 #
b10 &
#30
14
05
b0 *
0.
b10 "
b10 )
0-
00
0/
1+
b11 #
b11 &
#40
1=
16
19
15
b11 *
1.
1-
10
14
b11 "
b11 )
0<
1/
07
1?
0+
02
1:
b100 #
b100 &
#50
1<
0=
06
09
04
05
b0 *
0.
b100 "
b100 )
0-
00
0/
1+
b101 #
b101 &
#60
15
b1 *
1.
1-
10
b101 "
b101 )
04
1/
17
0+
12
b110 #
b110 &
#70
14
05
b0 *
0.
b110 "
b110 )
0-
00
0/
1+
b111 #
b111 &
#80
1E
1>
1A
1=
16
19
15
b111 *
1.
1-
10
14
1<
b111 "
b111 )
0D
1/
07
0?
1G
0+
02
0:
1B
b1000 #
b1000 &
#90
1D
0E
0>
0A
0<
0=
06
09
04
05
b0 *
0.
b1000 "
b1000 )
0-
00
0/
1+
b1001 #
b1001 &
#100
15
b1 *
1.
1-
10
b1001 "
b1001 )
04
1/
17
0+
12
b1010 #
b1010 &
#110
14
05
b0 *
0.
b1010 "
b1010 )
0-
00
0/
1+
b1011 #
b1011 &
#120
1=
16
19
15
b11 *
1.
1-
10
14
b1011 "
b1011 )
0<
1/
07
1?
0+
02
1:
b1100 #
b1100 &
#130
1<
0=
06
09
04
05
b0 *
0.
b1100 "
b1100 )
0-
00
0/
1+
b1101 #
b1101 &
#140
15
b1 *
1.
1-
10
b1101 "
b1101 )
04
1/
17
0+
12
b1110 #
b1110 &
#150
14
05
b0 *
0.
b1110 "
b1110 )
0-
00
0/
1+
b1111 #
b1111 &
#160
1M
1F
1I
1E
1>
1A
1=
16
19
15
b1111 *
1.
1-
10
14
1<
1D
b1111 "
b1111 )
0L
1/
07
0?
0G
1O
0+
02
0:
0B
1J
b10000 #
b10000 &
#170
1L
0M
0F
0I
0D
0E
0>
0A
0<
0=
06
09
04
05
b0 *
0.
b10000 "
b10000 )
0-
00
0/
1+
b10001 #
b10001 &
#180
15
b1 *
1.
1-
10
b10001 "
b10001 )
04
1/
17
0+
12
b10010 #
b10010 &
#190
14
05
b0 *
0.
b10010 "
b10010 )
0-
00
0/
1+
b10011 #
b10011 &
#200
1=
16
19
15
b11 *
1.
1-
10
14
b10011 "
b10011 )
0<
1/
07
1?
0+
02
1:
b10100 #
b10100 &
#210
1<
0=
06
09
04
05
b0 *
0.
b10100 "
b10100 )
0-
00
0/
1+
b10101 #
b10101 &
#220
15
b1 *
1.
1-
10
b10101 "
b10101 )
04
1/
17
0+
12
b10110 #
b10110 &
#230
14
05
b0 *
0.
b10110 "
b10110 )
0-
00
0/
1+
b10111 #
b10111 &
#240
1E
1>
1A
1=
16
19
15
b111 *
1.
1-
10
14
1<
b10111 "
b10111 )
0D
1/
07
0?
1G
0+
02
0:
1B
b11000 #
b11000 &
#250
1D
0E
0>
0A
0<
0=
06
09
04
05
b0 *
0.
b11000 "
b11000 )
0-
00
0/
1+
b11001 #
b11001 &
#260
15
b1 *
1.
1-
10
b11001 "
b11001 )
04
1/
17
0+
12
b11010 #
b11010 &
#270
14
05
b0 *
0.
b11010 "
b11010 )
0-
00
0/
1+
b11011 #
b11011 &
#280
1=
16
19
15
b11 *
1.
1-
10
14
b11011 "
b11011 )
0<
1/
07
1?
0+
02
1:
b11100 #
b11100 &
#290
1<
0=
06
09
04
05
b0 *
0.
b11100 "
b11100 )
0-
00
0/
1+
b11101 #
b11101 &
#300
15
b1 *
1.
1-
10
b11101 "
b11101 )
04
1/
17
0+
12
b11110 #
b11110 &
#310
14
05
b0 *
0.
b11110 "
b11110 )
0-
00
0/
1+
b11111 #
b11111 &
#320
1U
1N
1Q
1M
1F
1I
1E
1>
1A
1=
16
19
15
b11111 *
1.
1-
10
14
1<
1D
1L
b11111 "
b11111 )
0T
1/
07
0?
0G
0O
1W
0+
02
0:
0B
0J
1R
b100000 #
b100000 &
#330
1T
0U
0N
0Q
0L
0M
0F
0I
0D
0E
0>
0A
0<
0=
06
09
04
05
b0 *
0.
b100000 "
b100000 )
0-
00
0/
1+
b100001 #
b100001 &
#340
15
b1 *
1.
1-
10
b100001 "
b100001 )
04
1/
17
0+
12
b100010 #
b100010 &
#350
14
05
b0 *
0.
b100010 "
b100010 )
0-
00
0/
1+
b100011 #
b100011 &
#360
1=
16
19
15
b11 *
1.
1-
10
14
b100011 "
b100011 )
0<
1/
07
1?
0+
02
1:
b100100 #
b100100 &
#370
1<
0=
06
09
04
05
b0 *
0.
b100100 "
b100100 )
0-
00
0/
1+
b100101 #
b100101 &
#380
15
b1 *
1.
1-
10
b100101 "
b100101 )
04
1/
17
0+
12
b100110 #
b100110 &
#390
14
05
b0 *
0.
b100110 "
b100110 )
0-
00
0/
1+
b100111 #
b100111 &
#400
1E
1>
1A
1=
16
19
15
b111 *
1.
1-
10
14
1<
b100111 "
b100111 )
0D
1/
07
0?
1G
0+
02
0:
1B
b101000 #
b101000 &
#410
1D
0E
0>
0A
0<
0=
06
09
04
05
b0 *
0.
b101000 "
b101000 )
0-
00
0/
1+
b101001 #
b101001 &
#420
15
b1 *
1.
1-
10
b101001 "
b101001 )
04
1/
17
0+
12
b101010 #
b101010 &
#430
14
05
b0 *
0.
b101010 "
b101010 )
0-
00
0/
1+
b101011 #
b101011 &
#440
1=
16
19
15
b11 *
1.
1-
10
14
b101011 "
b101011 )
0<
1/
07
1?
0+
02
1:
b101100 #
b101100 &
#450
1<
0=
06
09
04
05
b0 *
0.
b101100 "
b101100 )
0-
00
0/
1+
b101101 #
b101101 &
#460
15
b1 *
1.
1-
10
b101101 "
b101101 )
04
1/
17
0+
12
b101110 #
b101110 &
#470
14
05
b0 *
0.
b101110 "
b101110 )
0-
00
0/
1+
b101111 #
b101111 &
#480
1M
1F
1I
1E
1>
1A
1=
16
19
15
b1111 *
1.
1-
10
14
1<
1D
b101111 "
b101111 )
0L
1/
07
0?
0G
1O
0+
02
0:
0B
1J
b110000 #
b110000 &
#490
1L
0M
0F
0I
0D
0E
0>
0A
0<
0=
06
09
04
05
b0 *
0.
b110000 "
b110000 )
0-
00
0/
1+
b110001 #
b110001 &
#500
15
b1 *
1.
1-
10
b110001 "
b110001 )
04
1/
17
0+
12
b110010 #
b110010 &
#510
14
05
b0 *
0.
b110010 "
b110010 )
0-
00
0/
1+
b110011 #
b110011 &
#520
1=
16
19
15
b11 *
1.
1-
10
14
b110011 "
b110011 )
0<
1/
07
1?
0+
02
1:
b110100 #
b110100 &
#530
1<
0=
06
09
04
05
b0 *
0.
b110100 "
b110100 )
0-
00
0/
1+
b110101 #
b110101 &
#540
15
b1 *
1.
1-
10
b110101 "
b110101 )
04
1/
17
0+
12
b110110 #
b110110 &
#550
14
05
b0 *
0.
b110110 "
b110110 )
0-
00
0/
1+
b110111 #
b110111 &
#560
1E
1>
1A
1=
16
19
15
b111 *
1.
1-
10
14
1<
b110111 "
b110111 )
0D
1/
07
0?
1G
0+
02
0:
1B
b111000 #
b111000 &
#570
1D
0E
0>
0A
0<
0=
06
09
04
05
b0 *
0.
b111000 "
b111000 )
0-
00
0/
1+
b111001 #
b111001 &
#580
15
b1 *
1.
1-
10
b111001 "
b111001 )
04
1/
17
0+
12
b111010 #
b111010 &
#590
14
05
b0 *
0.
b111010 "
b111010 )
0-
00
0/
1+
b111011 #
b111011 &
#600
1=
16
19
15
b11 *
1.
1-
10
14
b111011 "
b111011 )
0<
1/
07
1?
0+
02
1:
b111100 #
b111100 &
#610
1<
0=
06
09
04
05
b0 *
0.
b111100 "
b111100 )
0-
00
0/
1+
b111101 #
b111101 &
#620
15
b1 *
1.
1-
10
b111101 "
b111101 )
04
1/
17
0+
12
b111110 #
b111110 &
#630
14
05
b0 *
0.
b111110 "
b111110 )
0-
00
0/
1+
b111111 #
b111111 &
#640
1]
1V
1Y
1U
1N
1Q
1M
1F
1I
1E
1>
1A
1=
16
19
15
b111111 *
1.
1-
10
14
1<
1D
1L
1T
b111111 "
b111111 )
0\
1/
07
0?
0G
0O
0W
1_
0+
02
0:
0B
0J
0R
1Z
b1000000 #
b1000000 &
#650
1\
0]
0V
0Y
0T
0U
0N
0Q
0L
0M
0F
0I
0D
0E
0>
0A
0<
0=
06
09
04
05
b0 *
0.
b1000000 "
b1000000 )
0-
00
0/
1+
b1000001 #
b1000001 &
#660
15
b1 *
1.
1-
10
b1000001 "
b1000001 )
04
1/
17
0+
12
b1000010 #
b1000010 &
#670
14
05
b0 *
0.
b1000010 "
b1000010 )
0-
00
0/
1+
b1000011 #
b1000011 &
#680
1=
16
19
15
b11 *
1.
1-
10
14
b1000011 "
b1000011 )
0<
1/
07
1?
0+
02
1:
b1000100 #
b1000100 &
#690
1<
0=
06
09
04
05
b0 *
0.
b1000100 "
b1000100 )
0-
00
0/
1+
b1000101 #
b1000101 &
#700
15
b1 *
1.
1-
10
b1000101 "
b1000101 )
04
1/
17
0+
12
b1000110 #
b1000110 &
#710
14
05
b0 *
0.
b1000110 "
b1000110 )
0-
00
0/
1+
b1000111 #
b1000111 &
#720
1E
1>
1A
1=
16
19
15
b111 *
1.
1-
10
14
1<
b1000111 "
b1000111 )
0D
1/
07
0?
1G
0+
02
0:
1B
b1001000 #
b1001000 &
#730
1D
0E
0>
0A
0<
0=
06
09
04
05
b0 *
0.
b1001000 "
b1001000 )
0-
00
0/
1+
b1001001 #
b1001001 &
#740
15
b1 *
1.
1-
10
b1001001 "
b1001001 )
04
1/
17
0+
12
b1001010 #
b1001010 &
#750
14
05
b0 *
0.
b1001010 "
b1001010 )
0-
00
0/
1+
b1001011 #
b1001011 &
#760
1=
16
19
15
b11 *
1.
1-
10
14
b1001011 "
b1001011 )
0<
1/
07
1?
0+
02
1:
b1001100 #
b1001100 &
#770
1<
0=
06
09
04
05
b0 *
0.
b1001100 "
b1001100 )
0-
00
0/
1+
b1001101 #
b1001101 &
#780
15
b1 *
1.
1-
10
b1001101 "
b1001101 )
04
1/
17
0+
12
b1001110 #
b1001110 &
#790
14
05
b0 *
0.
b1001110 "
b1001110 )
0-
00
0/
1+
b1001111 #
b1001111 &
#800
1M
1F
1I
1E
1>
1A
1=
16
19
15
b1111 *
1.
1-
10
14
1<
1D
b1001111 "
b1001111 )
0L
1/
07
0?
0G
1O
0+
02
0:
0B
1J
b1010000 #
b1010000 &
#810
1L
0M
0F
0I
0D
0E
0>
0A
0<
0=
06
09
04
05
b0 *
0.
b1010000 "
b1010000 )
0-
00
0/
1+
b1010001 #
b1010001 &
#820
15
b1 *
1.
1-
10
b1010001 "
b1010001 )
04
1/
17
0+
12
b1010010 #
b1010010 &
#830
14
05
b0 *
0.
b1010010 "
b1010010 )
0-
00
0/
1+
b1010011 #
b1010011 &
#840
1=
16
19
15
b11 *
1.
1-
10
14
b1010011 "
b1010011 )
0<
1/
07
1?
0+
02
1:
b1010100 #
b1010100 &
#850
1<
0=
06
09
04
05
b0 *
0.
b1010100 "
b1010100 )
0-
00
0/
1+
b1010101 #
b1010101 &
#860
15
b1 *
1.
1-
10
b1010101 "
b1010101 )
04
1/
17
0+
12
b1010110 #
b1010110 &
#870
14
05
b0 *
0.
b1010110 "
b1010110 )
0-
00
0/
1+
b1010111 #
b1010111 &
#880
1E
1>
1A
1=
16
19
15
b111 *
1.
1-
10
14
1<
b1010111 "
b1010111 )
0D
1/
07
0?
1G
0+
02
0:
1B
b1011000 #
b1011000 &
#890
1D
0E
0>
0A
0<
0=
06
09
04
05
b0 *
0.
b1011000 "
b1011000 )
0-
00
0/
1+
b1011001 #
b1011001 &
#900
15
b1 *
1.
1-
10
b1011001 "
b1011001 )
04
1/
17
0+
12
b1011010 #
b1011010 &
#910
14
05
b0 *
0.
b1011010 "
b1011010 )
0-
00
0/
1+
b1011011 #
b1011011 &
#920
1=
16
19
15
b11 *
1.
1-
10
14
b1011011 "
b1011011 )
0<
1/
07
1?
0+
02
1:
b1011100 #
b1011100 &
#930
1<
0=
06
09
04
05
b0 *
0.
b1011100 "
b1011100 )
0-
00
0/
1+
b1011101 #
b1011101 &
#940
15
b1 *
1.
1-
10
b1011101 "
b1011101 )
04
1/
17
0+
12
b1011110 #
b1011110 &
#950
14
05
b0 *
0.
b1011110 "
b1011110 )
0-
00
0/
1+
b1011111 #
b1011111 &
#960
1U
1N
1Q
1M
1F
1I
1E
1>
1A
1=
16
19
15
b11111 *
1.
1-
10
14
1<
1D
1L
b1011111 "
b1011111 )
0T
1/
07
0?
0G
0O
1W
0+
02
0:
0B
0J
1R
b1100000 #
b1100000 &
#970
1T
0U
0N
0Q
0L
0M
0F
0I
0D
0E
0>
0A
0<
0=
06
09
04
05
b0 *
0.
b1100000 "
b1100000 )
0-
00
0/
1+
b1100001 #
b1100001 &
#980
15
b1 *
1.
1-
10
b1100001 "
b1100001 )
04
1/
17
0+
12
b1100010 #
b1100010 &
#990
14
05
b0 *
0.
b1100010 "
b1100010 )
0-
00
0/
1+
b1100011 #
b1100011 &
#1000
1=
16
19
15
b11 *
1.
1-
10
14
b1100011 "
b1100011 )
0<
1/
07
1?
0+
02
1:
b1100100 #
b1100100 &
#1010
1<
0=
06
09
04
05
b0 *
0.
b1100100 "
b1100100 )
0-
00
0/
1+
b1100101 #
b1100101 &
#1020
15
b1 *
1.
1-
10
b1100101 "
b1100101 )
04
1/
17
0+
12
b1100110 #
b1100110 &
#1030
14
05
b0 *
0.
b1100110 "
b1100110 )
0-
00
0/
1+
b1100111 #
b1100111 &
#1040
1E
1>
1A
1=
16
19
15
b111 *
1.
1-
10
14
1<
b1100111 "
b1100111 )
0D
1/
07
0?
1G
0+
02
0:
1B
b1101000 #
b1101000 &
#1050
1D
0E
0>
0A
0<
0=
06
09
04
05
b0 *
0.
b1101000 "
b1101000 )
0-
00
0/
1+
b1101001 #
b1101001 &
#1060
15
b1 *
1.
1-
10
b1101001 "
b1101001 )
04
1/
17
0+
12
b1101010 #
b1101010 &
#1070
14
05
b0 *
0.
b1101010 "
b1101010 )
0-
00
0/
1+
b1101011 #
b1101011 &
#1080
1=
16
19
15
b11 *
1.
1-
10
14
b1101011 "
b1101011 )
0<
1/
07
1?
0+
02
1:
b1101100 #
b1101100 &
#1090
1<
0=
06
09
04
05
b0 *
0.
b1101100 "
b1101100 )
0-
00
0/
1+
b1101101 #
b1101101 &
#1100
15
b1 *
1.
1-
10
b1101101 "
b1101101 )
04
1/
17
0+
12
b1101110 #
b1101110 &
#1110
14
05
b0 *
0.
b1101110 "
b1101110 )
0-
00
0/
1+
b1101111 #
b1101111 &
#1120
1M
1F
1I
1E
1>
1A
1=
16
19
15
b1111 *
1.
1-
10
14
1<
1D
b1101111 "
b1101111 )
0L
1/
07
0?
0G
1O
0+
02
0:
0B
1J
b1110000 #
b1110000 &
#1130
1L
0M
0F
0I
0D
0E
0>
0A
0<
0=
06
09
04
05
b0 *
0.
b1110000 "
b1110000 )
0-
00
0/
1+
b1110001 #
b1110001 &
#1140
15
b1 *
1.
1-
10
b1110001 "
b1110001 )
04
1/
17
0+
12
b1110010 #
b1110010 &
#1150
14
05
b0 *
0.
b1110010 "
b1110010 )
0-
00
0/
1+
b1110011 #
b1110011 &
#1160
1=
16
19
15
b11 *
1.
1-
10
14
b1110011 "
b1110011 )
0<
1/
07
1?
0+
02
1:
b1110100 #
b1110100 &
#1170
1<
0=
06
09
04
05
b0 *
0.
b1110100 "
b1110100 )
0-
00
0/
1+
b1110101 #
b1110101 &
#1180
15
b1 *
1.
1-
10
b1110101 "
b1110101 )
04
1/
17
0+
12
b1110110 #
b1110110 &
#1190
14
05
b0 *
0.
b1110110 "
b1110110 )
0-
00
0/
1+
b1110111 #
b1110111 &
#1200
1E
1>
1A
1=
16
19
15
b111 *
1.
1-
10
14
1<
b1110111 "
b1110111 )
0D
1/
07
0?
1G
0+
02
0:
1B
b1111000 #
b1111000 &
#1210
1D
0E
0>
0A
0<
0=
06
09
04
05
b0 *
0.
b1111000 "
b1111000 )
0-
00
0/
1+
b1111001 #
b1111001 &
#1220
15
b1 *
1.
1-
10
b1111001 "
b1111001 )
04
1/
17
0+
12
b1111010 #
b1111010 &
#1230
14
05
b0 *
0.
b1111010 "
b1111010 )
0-
00
0/
1+
b1111011 #
b1111011 &
#1240
1=
16
19
15
b11 *
1.
1-
10
14
b1111011 "
b1111011 )
0<
1/
07
1?
0+
02
1:
b1111100 #
b1111100 &
#1250
1<
0=
06
09
04
05
b0 *
0.
b1111100 "
b1111100 )
0-
00
0/
1+
b1111101 #
b1111101 &
#1260
15
b1 *
1.
1-
10
b1111101 "
b1111101 )
04
1/
17
0+
12
b1111110 #
b1111110 &
#1270
14
05
b0 *
0.
b1111110 "
b1111110 )
0-
00
0/
1+
b1111111 #
b1111111 &
#1280
1e
1^
1a
1]
1V
1Y
1U
1N
1Q
1M
1F
1I
1E
1>
1A
1=
16
19
15
b1111111 *
1.
1-
10
14
1<
1D
1L
1T
1\
b1111111 "
b1111111 )
0d
1/
07
0?
0G
0O
0W
0_
1g
0+
02
0:
0B
0J
0R
0Z
1b
b10000000 #
b10000000 &
#1290
b1 !
1(
b11111111 *
1f
1i
b11111111 "
b11111111 )
1d
0g
1c
b10000001 $
b10000001 '
#1300
05
09
0-
b11111110 *
0.
b11111110 "
b11111110 )
14
0/
00
17
18
0,
13
b10000010 $
b10000010 '
#1310
04
15
b11111101 "
b11111101 )
1-
b11111111 *
1.
1/
10
1,
b10000011 $
b10000011 '
