programas/restadorCompleto.v
module restadorCompleto(a, b, inBorr, d, outBorr );
    input a, b, inBorr;
    output d, outBorr;
    wire wire1, wire2, wire3;
    assign reg1=a^b;
    assign reg2=~(a)&b;
    assign reg3=~(reg1)&inBorr;
    assign d=reg1^inBorr;
    assign outBorr=reg2|reg3;
endmodule

testbenchs/basicas/restadorCompleto_tb.v
`timescale 1ns / 1ns
`include "restadorCompleto.v"

module restadorCompleto_tb;

reg a,b,c;
wire d,e;

restadorCompleto uut(a,b,c,d,e);

initial begin
    $dumpfile("restadorCompleto.vcd");
    $dumpvars(0, restadorCompleto_tb);

    a=0;
    b=0;
    c=0;
    #20;

    a=1;
    b=0;
    c=0;
    #20;

    a=0;
    b=1;
    c=0;
    #20;

    a=1;
    b=1;
    c=0;
    #20;

    a=0;
    b=0;
    c=1;
    #20;

    a=1;
    b=0;
    c=1;
    #20;

    a=0;
    b=1;
    c=1;
    #20;

    a=1;
    b=1;
    c=1;
    #20;
    $display("test complete");
end
endmodule

testbenchs/basicas/restadorCompleto.vcd
$date
	Wed Nov 09 16:52:17 2022
$end
$version
	Icarus Verilog
$end
$timescale
	1ns
$end
$scope module restadorCompleto_tb $end
$var wire 1 ! e $end
$var wire 1 " d $end
$var reg 1 # a $end
$var reg 1 $ b $end
$var reg 1 % c $end
$scope module uut $end
$var wire 1 # a $end
$var wire 1 $ b $end
$var wire 1 " d $end
$var wire 1 % inBorr $end
$var wire 1 ! outBorr $end
$var wire 1 & reg1 $end
$var wire 1 ' reg2 $end
$var wire 1 ( reg3 $end
$upscope $end
$upscope $end
$enddefinitions $end
#0
$dumpvars
0(
0'
0&
0%
0$
0#
0"
0!
$end
#20
1"
1&
1#
#40
1!
1'
1$
0#
#60
0!
0"
0'
0&
1#
#80
1!
1(
1"
1%
0$
0#
#100
0!
0(
0"
1&
1#
#120
1!
1'
1$
0#
#140
1(
1!
1"
0'
0&
1#
