alu_sum_res_mul/fullAdder.v
module fullAdder(a,b,c,d,e);
    input a,b,c;
    output d,e;
    wire reg1,reg2,reg3;
    assign reg1=a^b;
    assign reg2=a&b;
    assign reg3=reg1&c;
    assign d=reg1^c;
    assign e=reg2|reg3;
endmodule

testbenchs/basicas/fullAdder_tb.v
`timescale 1ns / 1ns
`include "fullAdder.v"

module hola_tb;

reg a,b,c;
wire d,e;

fullAdder uut(a,b,c,d,e);

initial begin
    $dumpfile("fullAdder.vcd");
    $dumpvars(0, hola_tb);

    a=0;
    b=0;
    c=0;
    #20;

    a=1;
    b=0;
    c=0;
    #20;

    a=0;
    b=1;
    c=0;
    #20;

    a=1;
    b=1;
    c=0;
    #20;

    a=0;
    b=0;
    c=1;
    #20;

    a=1;
    b=0;
    c=1;
    #20;

    a=0;
    b=1;
    c=1;
    #20;

    a=1;
    b=1;
    c=1;
    #20;
    $display("test complete");
end
endmodule

testbenchs/extas/hola.vcd
$date
	Sun Aug 28 21:28:25 2022
$end
$version
	Icarus Verilog
$end
$timescale
	1ns
$end
$scope module hola_tb $end
$var wire 1 ! e $end
$var wire 1 " d $end
$var reg 1 # a $end
$var reg 1 $ b $end
$var reg 1 % c $end
$scope module uut $end
$var wire 1 # a $end
$var wire 1 $ b $end
$var wire 1 % c $end
$var wire 1 " d $end
$var wire 1 ! e $end
$var wire 1 & reg1 $end
$var wire 1 ' reg2 $end
$var wire 1 ( reg3 $end
$upscope $end
$upscope $end
$enddefinitions $end
$comment Show the parameter values. $end
$dumpall
$end
#0
$dumpvars
0(
0'
0&
0%
0$
0#
0"
0!
$end
#20
1"
1&
1#
#40
1$
0#
#60
0"
1!
0&
1'
1#
#80
0!
1"
0'
1%
0$
0#
#100
1!
1(
0"
1&
1#
#120
1$
0#
#140
0(
1"
0&
1'
1#
